pyvotal
