Metadata-Version: 1.0
Name: pyvotal
Version: 0.2
Summary: Pivotal tracker api client. https://www.pivotaltracker.com/help/api?version=v3
Home-page: https://github.com/fullboar/pyvotal
Author: Anatoly Kudinov
Author-email: zz@rialabs.org
License: Apache 2.0
Platform: UNKNOWN
